opentype_feature_freezer/__init__.py
opentype_feature_freezer/cli.py
opentype_feature_freezer-1.32.2.dist-info/entry_points.txt
opentype_feature_freezer-1.32.2.dist-info/LICENSE
opentype_feature_freezer-1.32.2.dist-info/WHEEL
opentype_feature_freezer-1.32.2.dist-info/METADATA
opentype_feature_freezer-1.32.2.dist-info/RECORD
