Metadata-Version: 2.1
Name: opentype-feature-freezer
Version: 1.32.2
Summary: Turns OpenType features 'on' by default in a font: reassigns the font's Unicode-to-glyph mapping fo permanently 'freeze' the 1-to-1 substitution features, and creates a new font.
License: Apache-2.0
Author: Adam Twardoch
Author-email: adam@twardoch.com
Requires-Python: >=3.6,<4.0
Classifier: License :: OSI Approved :: Apache Software License
Classifier: Programming Language :: Python :: 3
Classifier: Programming Language :: Python :: 3.6
Classifier: Programming Language :: Python :: 3.7
Classifier: Programming Language :: Python :: 3.8
Requires-Dist: fonttools (>=4.0,<5.0)
